README.md
setup.py
lppypi/lppypi.py
lppypi.egg-info/PKG-INFO
lppypi.egg-info/SOURCES.txt
lppypi.egg-info/dependency_links.txt
lppypi.egg-info/entry_points.txt
lppypi.egg-info/top_level.txt
lppypi.egg-info/zip-safe