Metadata-Version: 2.1
Name: lppypi
Version: 0.0.1
Summary: lppypi
Home-page: https://github.com/vcancy/spider80s
Author: liupeng
Author-email: lp3799@163.com
License: MIT
Keywords: lppypi
Platform: UNKNOWN
Classifier: License :: OSI Approved :: MIT License
Classifier: Programming Language :: Python
Classifier: Intended Audience :: Developers
Classifier: Operating System :: OS Independent
